madevent7/__init__.py
madevent7/_madevent_py.cpython-311-x86_64-linux-gnu.so
madevent7/_madevent_py.pyi
madevent7/_madevent_py_loader.py
madevent7/madnis.py
madevent7/torch.py
madevent7/include/madevent/constants.h
madevent7/include/madevent/madcode.h
madevent7/include/madevent/phasespace.h
madevent7/include/madevent/runtime.h
madevent7/include/madevent/umami.h
madevent7/include/madevent/util.h
madevent7/include/madevent/madcode/function.h
madevent7/include/madevent/madcode/function_builder_mixin.h
madevent7/include/madevent/madcode/instruction.h
madevent7/include/madevent/madcode/opcode_mixin.h
madevent7/include/madevent/madcode/optimizer.h
madevent7/include/madevent/madcode/type.h
madevent7/include/madevent/phasespace/base.h
madevent7/include/madevent/phasespace/channel_weight_network.h
madevent7/include/madevent/phasespace/channel_weights.h
madevent7/include/madevent/phasespace/chili.h
madevent7/include/madevent/phasespace/cross_section.h
madevent7/include/madevent/phasespace/cuts.h
madevent7/include/madevent/phasespace/discrete_flow.h
madevent7/include/madevent/phasespace/discrete_sampler.h
madevent7/include/madevent/phasespace/flow.h
madevent7/include/madevent/phasespace/integrand.h
madevent7/include/madevent/phasespace/invariants.h
madevent7/include/madevent/phasespace/luminosity.h
madevent7/include/madevent/phasespace/matrix_element.h
madevent7/include/madevent/phasespace/mlp.h
madevent7/include/madevent/phasespace/multichannel.h
madevent7/include/madevent/phasespace/pdf.h
madevent7/include/madevent/phasespace/phasespace.h
madevent7/include/madevent/phasespace/rambo.h
madevent7/include/madevent/phasespace/scale.h
madevent7/include/madevent/phasespace/t_propagator_mapping.h
madevent7/include/madevent/phasespace/three_particle.h
madevent7/include/madevent/phasespace/topology.h
madevent7/include/madevent/phasespace/two_particle.h
madevent7/include/madevent/phasespace/vegas.h
madevent7/include/madevent/runtime/context.h
madevent7-0.2.3.dist-info/METADATA
madevent7-0.2.3.dist-info/WHEEL
madevent7-0.2.3.dist-info/RECORD
madevent7-0.2.3.dist-info/licenses/LICENSE
