Metadata-Version: 2.1
Name: madevent7
Version: 0.2.3
Summary: Fast and flexible phase space mappings
Author-Email: Theo Heimel <theo.heimel@uclouvain.be>
Classifier: Programming Language :: Python :: 3
Classifier: License :: OSI Approved :: MIT License
Classifier: Operating System :: OS Independent
Requires-Python: >=3.11
